{
  "all":20,
  "msg":[
    {
      "user": {
        "user-img": "src/img/logo.png",
        "user-name": "zJY"
      },
      "comment": {
        "content": "这是评论，我还不知道说什么好。这是评论，我还不知道说什么好。这是评论，我还不知道说什么好。",
        "time": "12/20 12:30"
      }
    },
    {
      "user": {
        "user-img": "src/img/logo.png",
        "user-name": "zJY"
      },
      "comment": {
        "content": "这是评论，我还不知道说什么好。这是评论，我还不知道说什么好。这是评论，我还不知道说什么好。",
        "time": "12/20 12:30"
      }
    },
    {
      "user": {
        "user-img": "src/img/logo.png",
        "user-name": "zJY"
      },
      "comment": {
        "content": "这是评论，我还不知道说什么好。这是评论，我还不知道说什么好。这是评论，我还不知道说什么好。",
        "time": "12/20 12:30"
      }
    },
    {
      "user": {
        "user-img": "src/img/logo.png",
        "user-name": "zJY"
      },
      "comment": {
        "content": "这是评论，我还不知道说什么好。这是评论，我还不知道说什么好。这是评论，我还不知道说什么好。",
        "time": "12/20 12:30"
      }
    },
    {
      "user": {
        "user-img": "src/img/logo.png",
        "user-name": "zJY"
      },
      "comment": {
        "content": "这是评论，我还不知道说什么好。这是评论，我还不知道说什么好。这是评论，我还不知道说什么好。",
        "time": "12/20 12:30"
      }
    }
  ]
}